textcomplexity/__init__.py
textcomplexity/textcomplexity.py
textcomplexity_riyaribadia1-0.1.0.dist-info/licenses/LICENSE
textcomplexity_riyaribadia1-0.1.0.dist-info/METADATA
textcomplexity_riyaribadia1-0.1.0.dist-info/WHEEL
textcomplexity_riyaribadia1-0.1.0.dist-info/top_level.txt
textcomplexity_riyaribadia1-0.1.0.dist-info/RECORD
