Metadata-Version: 2.4
Name: textcomplexity-RiyaRibadia1
Version: 0.1.0
Summary: A lightweight readability and complexity analyzer for English text.
Author-email: Riya Ribadia <ribadiariya@gmail.com>
License: MIT License
Project-URL: Homepage, https://pypi.org/project/textcomplexity/
Project-URL: Repository, https://github.com/RibadiaRiya/textcomplexity
Requires-Python: >=3.7
License-File: LICENSE
Dynamic: license-file
